presidio_structured/__init__.py
presidio_structured/analysis_builder.py
presidio_structured/config/__init__.py
presidio_structured/config/structured_analysis.py
presidio_structured/data/__init__.py
presidio_structured/data/data_processors.py
presidio_structured/data/data_reader.py
presidio_structured/py.typed
presidio_structured/structured_engine.py
presidio_structured-0.0.6.dist-info/METADATA
presidio_structured-0.0.6.dist-info/WHEEL
presidio_structured-0.0.6.dist-info/RECORD
