Metadata-Version: 2.3
Name: presidio_structured
Version: 0.0.6
Summary: Presidio structured package - analyzes and anonymizes structured and semi-structured data.
License: MIT
Keywords: presidio_structured
Author: Presidio
Author-email: presidio@microsoft.com
Requires-Python: >=3.9,<4.0
Classifier: License :: OSI Approved :: MIT License
Classifier: Operating System :: OS Independent
Classifier: Programming Language :: Python :: 3.9
Classifier: Programming Language :: Python :: 3.10
Classifier: Programming Language :: Python :: 3.11
Classifier: Programming Language :: Python :: 3.12
Requires-Dist: pandas (>=1.5.2)
Requires-Dist: presidio-analyzer (>=2.2)
Requires-Dist: presidio-anonymizer (>=2.2)
Requires-Dist: spacy (<3.8.4) ; python_version < "3.10"
Project-URL: Homepage, https://github.com/microsoft/presidio
